courseaffils/__init__.py
courseaffils/admin.py
courseaffils/columbia.py
courseaffils/forms.py
courseaffils/lib.py
courseaffils/listener.py
courseaffils/middleware.py
courseaffils/models.py
courseaffils/utils.py
courseaffils/views.py
courseaffils/migrations/0001_initial.py
courseaffils/migrations/0002_auto_20160316_1223.py
courseaffils/migrations/0003_auto_20160429_1353.py
courseaffils/migrations/0004_auto_20170623_1231.py
courseaffils/migrations/0005_auto_20200318_1543.py
courseaffils/migrations/__init__.py
courseaffils/templates/base.html
courseaffils/templates/courseaffils/admin_change_form.html
courseaffils/templates/courseaffils/course_form.html
courseaffils/templates/courseaffils/course_list.html
courseaffils/templates/courseaffils/course_row.html
courseaffils/templatetags/__init__.py
courseaffils/templatetags/coursetags.py
courseaffils/tests/__init__.py
courseaffils/tests/factories.py
courseaffils/tests/mixins.py
courseaffils/tests/test_columbia.py
courseaffils/tests/test_forms.py
courseaffils/tests/test_lib.py
courseaffils/tests/test_listener.py
courseaffils/tests/test_middleware.py
courseaffils/tests/test_models.py
courseaffils/tests/test_settings.py
courseaffils/tests/test_utils.py
courseaffils/tests/test_views.py
courseaffils/tests/urls.py
django_courseaffils-2.5.1.dist-info/METADATA
django_courseaffils-2.5.1.dist-info/WHEEL
django_courseaffils-2.5.1.dist-info/top_level.txt
django_courseaffils-2.5.1.dist-info/RECORD
