Metadata-Version: 2.4
Name: django-courseaffils
Version: 2.5.1
Summary: course affiliations
Home-page: https://github.com/ccnmtl/django_courseaffils/
Author: Columbia University's Center for Teaching and Learning
Author-email: ctl-dev@columbia.edu
Requires-Dist: Django
Dynamic: author
Dynamic: author-email
Dynamic: description
Dynamic: home-page
Dynamic: keywords
Dynamic: requires-dist
Dynamic: summary
